Metadata-Version: 2.1
Name: vermanager
Version: 0.1.3
Summary: A manager for versions. Modules with version requirements can be written as `ModuleName(==|>=|<=)1.2.3`. The VerManager is aimed at version control. 
Home-page: https://gitee.com/junruoyu-zheng/ver-manager
Author: junruoyu-zheng
Author-email: zhengjry@outlook.com
License: UNKNOWN
Platform: UNKNOWN
Classifier: Programming Language :: Python :: 3
Classifier: License :: OSI Approved :: MIT License
Classifier: Operating System :: OS Independent
